mat3ra/__init__.py
mat3ra/ide/__init__.py
mat3ra_ide-2025.11.16.post0.dist-info/licenses/LICENSE.md
mat3ra_ide-2025.11.16.post0.dist-info/METADATA
mat3ra_ide-2025.11.16.post0.dist-info/WHEEL
mat3ra_ide-2025.11.16.post0.dist-info/top_level.txt
mat3ra_ide-2025.11.16.post0.dist-info/RECORD
