Metadata-Version: 2.4
Name: mat3ra-ide
Version: 2025.11.16.post0
Summary: Infrastructure DEfinitions
Author-email: "Exabyte Inc." <info@mat3ra.com>
License: Apache-2.0
Classifier: Programming Language :: Python :: 3
Classifier: Programming Language :: Python :: 3.10
Classifier: Programming Language :: Python :: 3.11
Classifier: Programming Language :: Python :: 3.12
Classifier: Programming Language :: Python :: 3.13
Classifier: Development Status :: 3 - Alpha
Classifier: Topic :: Software Development
Requires-Python: >=3.10
License-File: LICENSE.md
Requires-Dist: numpy
Provides-Extra: tests
Requires-Dist: pytest>=7.0.0; extra == "tests"
Requires-Dist: pytest-cov; extra == "tests"
Requires-Dist: coverage[toml]>=6.0; extra == "tests"
Dynamic: license-file
